AUTHORS
CHANGELOG.txt
DESCRIPTION
LICENSE
MANIFEST.in
README.md
setup.cfg
setup.py
django_redirect_plus.egg-info/PKG-INFO
django_redirect_plus.egg-info/SOURCES.txt
django_redirect_plus.egg-info/dependency_links.txt
django_redirect_plus.egg-info/requires.txt
django_redirect_plus.egg-info/top_level.txt
redirect_plus/__init__.py
redirect_plus/admin.py
redirect_plus/middleware.py
redirect_plus/models.py
redirect_plus/urls.py
redirect_plus/views.py
redirect_plus/management/__init__.py
redirect_plus/management/commands/__init__.py
redirect_plus/management/commands/hello.py
redirect_plus/static/.empty
redirect_plus/static/redirct_plus/.empty
redirect_plus/templates/redirct_plus/.empty
redirect_plus/templatetags/__init__.py
redirect_plus/templatetags/redirct_plus_tags.py
redirect_plus/tests/__init__.py
redirect_plus/tests/factories.py
redirect_plus/tests/models_tests.py
redirect_plus/tests/runtests.py
redirect_plus/tests/south_settings.py
redirect_plus/tests/test_settings.py
redirect_plus/tests/urls.py
redirect_plus/tests/test_app/__init__.py
redirect_plus/tests/test_app/models.py
redirect_plus/tests/test_app/templates/400.html
redirect_plus/tests/test_app/templates/500.html