Metadata-Version: 1.0
Name: django-redirect-plus
Version: 0.0.1
Summary: Django's built-in redirect app with some extras.
